agilent_visa_control/__init__.py
agilent_visa_control/agilent.py
agilent_visa_control/frequency.py
agilent_visa_control-0.0.2.1.2.data/data/LICENSE
agilent_visa_control-0.0.2.1.2.dist-info/LICENSE
agilent_visa_control-0.0.2.1.2.dist-info/METADATA
agilent_visa_control-0.0.2.1.2.dist-info/WHEEL
agilent_visa_control-0.0.2.1.2.dist-info/top_level.txt
agilent_visa_control-0.0.2.1.2.dist-info/RECORD
