Metadata-Version: 2.1
Name: agilent-visa-control
Version: 0.0.2.1.2
Summary: A small package aimed at helping with interfacing with Agilent spectrum analyzer (tested with ESA and EXA series)
Home-page: https://github.com/emorell96/agilent_visa_control
Author: Enrique Morell
Author-email: morell.enrique@outlook.com
License: GNU General Public License v3 (GPLv3)
Platform: UNKNOWN
Classifier: Programming Language :: Python :: 3
Classifier: License :: OSI Approved :: GNU General Public License v3 (GPLv3)
Classifier: Operating System :: OS Independent
Requires-Dist: PyVISA (>=1.9)
